ply_parser/__init__.py
ply_parser/ply_parser.py
ply_parser/test_ply_parser.py
ply_parser-2.0.0.dist-info/METADATA
ply_parser-2.0.0.dist-info/WHEEL
ply_parser-2.0.0.dist-info/top_level.txt
ply_parser-2.0.0.dist-info/RECORD
