Metadata-Version: 2.1
Name: ply-parser
Version: 2.0.0
Summary: A python module that parses ascii PLY (.ply) (Polygon File Format) files. It includes a class PLYObject for storing PLY file data and a function parse_ply_file() for reading PLY files and creating PLYObject instances and can easily be customized.
Home-page: https://github.com/Qrishna/ply_parser
Author: Krishna Bhattarai
Author-email: Krishna Bhattarai <krishna@kbhattarai.com>
Project-URL: Homepage, https://github.com/Qrishna/ply_parser
Project-URL: Bug Tracker, https://github.com/Qrishna/ply_parser/issues
Classifier: Programming Language :: Python :: 3
Classifier: License :: OSI Approved :: MIT License
Classifier: Operating System :: OS Independent
Requires-Python: >=3.11.4
